[
    {
        "imageUrl": "/src/app/Images/WellnessImage.svg",
        "title":"WELLNESS PACKAGES"
    },
    {
        "imageUrl": "/src/app/Images/BoutiqueImage.svg",
        "title":"BOUTIQUE STAY RETREAT"
    },
    {
        "imageUrl": "/src/app/Images/DoctorImage.svg",
        "title":"DOCTOR CONSULTATION"
    },
    {
        "imageUrl": "/src/app/Images/CulturalImage.svg",
        "title":"CULTURAL RETREAT"
    },
    {
        "imageUrl": "/src/app/Images/YogaImage.svg",
        "title":"YOGA RETREAT"
    },
    {
        "imageUrl": "/src/app/Images/MedicalImage.svg",
        "title":"MEDICATION RETREAT"
    }
]